load_envfile/__init__.py
load_envfile/load_envfile.py
LoadEnvFileLib-0.4.dist-info/METADATA
LoadEnvFileLib-0.4.dist-info/WHEEL
LoadEnvFileLib-0.4.dist-info/top_level.txt
LoadEnvFileLib-0.4.dist-info/RECORD
